bthome_logger.py
bthome_logger-0.1.9.dist-info/METADATA
bthome_logger-0.1.9.dist-info/WHEEL
bthome_logger-0.1.9.dist-info/entry_points.txt
bthome_logger-0.1.9.dist-info/licenses/LICENSE
bthome_logger-0.1.9.dist-info/RECORD
