Metadata-Version: 2.4
Name: bthome-logger
Version: 0.1.9
Summary: BThome v2 BLE Advertisement Logger for debugging and monitoring BThome devices
Project-URL: Homepage, https://github.com/the78mole/bthomev2
Project-URL: Repository, https://github.com/the78mole/bthomev2
Project-URL: Issues, https://github.com/the78mole/bthomev2/issues
Project-URL: Documentation, https://github.com/the78mole/bthomev2/blob/main/tools/README.md
Author-email: Daniel Glaser <daniel.glaser@tu-ilmenau.de>
Maintainer-email: Daniel Glaser <daniel.glaser@tu-ilmenau.de>
License: MIT
License-File: LICENSE
Keywords: ble,bluetooth,bthome,home-assistant,iot
Classifier: Development Status :: 4 - Beta
Classifier: Intended Audience :: Developers
Classifier: License :: OSI Approved :: MIT License
Classifier: Programming Language :: Python :: 3
Classifier: Programming Language :: Python :: 3.8
Classifier: Programming Language :: Python :: 3.9
Classifier: Programming Language :: Python :: 3.10
Classifier: Programming Language :: Python :: 3.11
Classifier: Programming Language :: Python :: 3.12
Classifier: Topic :: Home Automation
Classifier: Topic :: System :: Monitoring
Requires-Python: >=3.8
Requires-Dist: bleak>=0.21.0
Requires-Dist: typer>=0.9.0
